README.md
setup.py
gossipy/__init__.py
gossipy/core.py
gossipy/flow_control.py
gossipy/node.py
gossipy/simul.py
gossipy/utils.py
gossipy/data/__init__.py
gossipy/data/handler.py
gossipy/model/__init__.py
gossipy/model/byzantine.py
gossipy/model/handler.py
gossipy/model/nn.py
gossipy/model/sampling.py
gossipy_dfl.egg-info/PKG-INFO
gossipy_dfl.egg-info/SOURCES.txt
gossipy_dfl.egg-info/dependency_links.txt
gossipy_dfl.egg-info/requires.txt
gossipy_dfl.egg-info/top_level.txt