Metadata-Version: 1.1
Name: gossipy-dfl
Version: 0.0.1
Summary: Python module for simulating gossip learning and decentralized federated learning.
Home-page: https://github.com/makgyver/gossipy
Author: Mirko Polato
Author-email: mirko.polato@unito.it
License: Apache License, Version 2.0
Platform: UNKNOWN
Classifier: Development Status :: 2 - Pre-Alpha
Classifier: Intended Audience :: Science/Research
Classifier: License :: OSI Approved :: Apache Software License
Classifier: Environment :: MacOS X
Classifier: Operating System :: MacOS
Classifier: Programming Language :: Python :: 3
Classifier: Programming Language :: Python :: 3.8
Classifier: Programming Language :: Python :: 3.9
